reynir_correct/__init__.py
reynir_correct/annotation.py
reynir_correct/checker.py
reynir_correct/classifier.py
reynir_correct/errfinder.py
reynir_correct/errtokenizer.py
reynir_correct/main.py
reynir_correct/pattern.py
reynir_correct/py.typed
reynir_correct/readability.py
reynir_correct/settings.py
reynir_correct/spelling.py
reynir_correct/wrappers.py
reynir_correct/config/GreynirCorrect.conf
reynir_correct/config/IEC_nonwords.tsv
reynir_correct/config/IceSQuErVersion01.tsv
reynir_correct/config/Storasnid_ritm.csv
reynir_correct/config/TabooWords.conf
reynir_correct/config/WrongWords.conf
reynir_correct/resources/iceloc_prep.json
reynir_correct/resources/nonwords.csv
reynir_correct/tools/diffchecker.py
reynir_correct/tools/ritmyndirchecker.py
reynir_correct-4.1.3.dist-info/licenses/LICENSE.txt
reynir_correct-4.1.3.dist-info/METADATA
reynir_correct-4.1.3.dist-info/WHEEL
reynir_correct-4.1.3.dist-info/entry_points.txt
reynir_correct-4.1.3.dist-info/top_level.txt
reynir_correct-4.1.3.dist-info/RECORD
