Metadata-Version: 2.4
Name: reynir-correct
Version: 4.1.3
Summary: Spelling and grammar correction for Icelandic
Author-email: "Miðeind ehf." <mideind@mideind.is>
License: MIT License
Project-URL: Repository, https://github.com/mideind/GreynirCorrect
Classifier: Development Status :: 5 - Production/Stable
Classifier: Intended Audience :: Developers
Classifier: Intended Audience :: Science/Research
Classifier: License :: OSI Approved :: MIT License
Classifier: Operating System :: Unix
Classifier: Operating System :: POSIX
Classifier: Operating System :: Microsoft :: Windows
Classifier: Operating System :: MacOS
Classifier: Natural Language :: Icelandic
Classifier: Programming Language :: Python
Classifier: Programming Language :: Python :: 3
Classifier: Programming Language :: Python :: 3.9
Classifier: Programming Language :: Python :: 3.10
Classifier: Programming Language :: Python :: 3.11
Classifier: Programming Language :: Python :: 3.12
Classifier: Programming Language :: Python :: 3.13
Classifier: Programming Language :: Python :: Implementation :: CPython
Classifier: Programming Language :: Python :: Implementation :: PyPy
Classifier: Topic :: Software Development :: Libraries :: Python Modules
Classifier: Topic :: Utilities
Classifier: Topic :: Text Processing :: Linguistic
Requires-Python: >=3.9
License-File: LICENSE.txt
Requires-Dist: reynir>=3.5.7
Requires-Dist: icegrams>=1.1.2
Requires-Dist: typing_extensions
Provides-Extra: dev
Requires-Dist: pytest; extra == "dev"
Provides-Extra: sentence-classifier
Requires-Dist: transformers; extra == "sentence-classifier"
Requires-Dist: datasets; extra == "sentence-classifier"
Requires-Dist: torch; extra == "sentence-classifier"
Dynamic: license-file
